{
  "id": "H1RIFSPABM03NA",
  "realtime_start": "2022-08-14",
  "realtime_end": "2022-08-14",
  "title": "Average Dealer Offering Rate on 3-Month Domestic Private Bankers' Acceptances, Quoted on a Discount Basis (DISCONTINUED)",
  "observation_start": "1965-01-01",
  "observation_end": "2000-01-01",
  "frequency": "Annual",
  "frequency_short": "A",
  "units": "Percent",
  "units_short": "%",
  "seasonal_adjustment": "Not Seasonally Adjusted",
  "seasonal_adjustment_short": "NSA",
  "last_updated": "2022-06-03 16:10:20-05",
  "popularity": 1,
  "group_popularity": 1,
  "notes": "Averages of daily figures.\n\nThe Federal Reserve Board has discontinued this series. For more information see the H.15 Statistical Release (https://www.federalreserve.gov/releases/h15/default.htm)."
}