{
  "id": "SPPOP0014TOZSHKG",
  "realtime_start": "2022-09-04",
  "realtime_end": "2022-09-04",
  "title": "Population Ages 0 to 14 for Hong Kong SAR, China",
  "observation_start": "1960-01-01",
  "observation_end": "2021-01-01",
  "frequency": "Annual",
  "frequency_short": "A",
  "units": "Percent of Total",
  "units_short": "% of Total",
  "seasonal_adjustment": "Not Seasonally Adjusted",
  "seasonal_adjustment_short": "NSA",
  "last_updated": "2022-07-05 14:32:35-05",
  "popularity": 1,
  "group_popularity": 1,
  "notes": "Source Indicator: SP.POP.0014.TO.ZS"
}