{
  "id": "LNU04000012",
  "realtime_start": "2022-08-21",
  "realtime_end": "2022-08-21",
  "title": "Unemployment Rate - 16-19 Yrs.",
  "observation_start": "1948-01-01",
  "observation_end": "2022-07-01",
  "frequency": "Monthly",
  "frequency_short": "M",
  "units": "Percent",
  "units_short": "%",
  "seasonal_adjustment": "Not Seasonally Adjusted",
  "seasonal_adjustment_short": "NSA",
  "last_updated": "2022-08-05 07:43:52-05",
  "popularity": 6,
  "group_popularity": 27,
  "notes": "The series comes from the 'Current Population Survey (Household Survey)'\n\nThe source code is: LNU04000012"
}