{
  "id": "ADPWES250T499ENERSA",
  "realtime_start": "2022-12-11",
  "realtime_end": "2022-12-11",
  "title": "Nonfarm Private Employment in Medium Establishments with 250 to 499 Employees",
  "observation_start": "2010-01-02",
  "observation_end": "2022-10-01",
  "frequency": "Weekly",
  "frequency_short": "W",
  "units": "Persons",
  "units_short": "Persons",
  "seasonal_adjustment": "Seasonally Adjusted",
  "seasonal_adjustment_short": "SA",
  "last_updated": "2022-11-30 07:26:20-06",
  "popularity": 1,
  "group_popularity": 2
}