{
  "id": "SMU72000006562000030",
  "realtime_start": "2022-05-01",
  "realtime_end": "2022-05-01",
  "title": "Average Weekly Earnings of Production Employees: Health Care and Social Assistance in Puerto Rico (DISCONTINUED)",
  "observation_start": "2001-01-01",
  "observation_end": "2013-12-01",
  "frequency": "Monthly",
  "frequency_short": "M",
  "units": "Dollars per Week",
  "units_short": "$ per Week",
  "seasonal_adjustment": "Not Seasonally Adjusted",
  "seasonal_adjustment_short": "NSA",
  "last_updated": "2014-02-02 01:51:45-06",
  "popularity": 1,
  "group_popularity": 1
}